django_collect_and_ignore
