Metadata-Version: 2.1
Name: django-collect-and-ignore
Version: 0.1.1
Summary: Custom collectstatic for django with ignoring commonly copied unnecessary files
Home-page: https://github.com/marinko-peso/django-collect-and-ignore
Author: Marinko Peso
Author-email: marinko.peso@gmail.com
License: MIT
Keywords: django collectstatic custom ignore
Platform: UNKNOWN
Classifier: Intended Audience :: Developers
Classifier: License :: OSI Approved :: MIT License
Classifier: Operating System :: OS Independent
Classifier: Programming Language :: Python
Classifier: Programming Language :: Python :: 2
Classifier: Programming Language :: Python :: 2.7
Classifier: Programming Language :: Python :: 3
Classifier: Programming Language :: Python :: 3.6
